xair_api/__init__.py
xair_api/adapter.py
xair_api/bus.py
xair_api/config.py
xair_api/dca.py
xair_api/errors.py
xair_api/fx.py
xair_api/headamp.py
xair_api/kinds.py
xair_api/lr.py
xair_api/meta.py
xair_api/rtn.py
xair_api/shared.py
xair_api/strip.py
xair_api/util.py
xair_api/xair.py
xair_api-2.4.0.dist-info/entry_points.txt
xair_api-2.4.0.dist-info/LICENSE
xair_api-2.4.0.dist-info/METADATA
xair_api-2.4.0.dist-info/WHEEL
xair_api-2.4.0.dist-info/RECORD
