Metadata-Version: 2.1
Name: xair-api
Version: 2.4.0
Summary: Remote control Behringer X-Air | Midas MR mixers through OSC
Home-page: https://github.com/onyx-and-iris/xair-api-python
License: MIT
Author: onyx-and-iris
Author-email: code@onyxandiris.online
Requires-Python: >=3.10,<4.0
Classifier: License :: OSI Approved :: MIT License
Classifier: Programming Language :: Python :: 3
Classifier: Programming Language :: Python :: 3.10
Classifier: Programming Language :: Python :: 3.11
Classifier: Programming Language :: Python :: 3.12
Classifier: Programming Language :: Python :: 3.13
Requires-Dist: python-osc (>=1.8.0,<2.0.0)
Requires-Dist: tomli (>=2.0.1,<3.0.0) ; python_version < "3.11"
Project-URL: Repository, https://github.com/onyx-and-iris/xair-api-python
